igz_mgmt/__init__.py
igz_mgmt/__version__.py
igz_mgmt/client.py
igz_mgmt/constants.py
igz_mgmt/cruds.py
igz_mgmt/exceptions.py
igz_mgmt/operations.py
igz_mgmt/resources.py
igz_mgmt/common/__init__.py
igz_mgmt/common/helpers.py
igz_mgmt/logger/__init__.py
igz_mgmt/logger/logger.py
igz_mgmt/schemas/__init__.py
igz_mgmt/schemas/app_services.py
igz_mgmt/schemas/events.py
igz_mgmt/schemas/limits.py
igz_mgmt/schemas/manual_events.py
igz_mgmt-0.4.2.dist-info/METADATA
igz_mgmt-0.4.2.dist-info/WHEEL
igz_mgmt-0.4.2.dist-info/licenses/LICENSE
igz_mgmt-0.4.2.dist-info/RECORD
