Metadata-Version: 2.4
Name: igz-mgmt
Version: 0.4.2
Summary: Python SDK For Iguazio Management API
Project-URL: Homepage, https://github.com/iguazio/igz-mgmt-sdk
Author-email: Iguazio Platform Team <liranb@iguazio.com>
License-Expression: Apache-2.0
License-File: LICENSE
Classifier: License :: OSI Approved :: Apache Software License
Classifier: Programming Language :: Python
Classifier: Programming Language :: Python :: 3
Requires-Python: >=3.9
Requires-Dist: deprecated~=1.2.15
Requires-Dist: httpx<0.29.0,>=0.27.2
Requires-Dist: inflection~=0.5.1
Requires-Dist: pydantic>=1.10.19
Requires-Dist: semver~=3.0.2
